CHANGELOG.md
LICENSE
MANIFEST.in
README.md
requirements.txt
setup.cfg
setup.py
tests/__init__.py
tests/test_help.py
tests/test_xhs.py
tests/utils.py
xhs/__init__.py
xhs/__version__.py
xhs/core.py
xhs/exception.py
xhs/help.py
xhs_client.egg-info/PKG-INFO
xhs_client.egg-info/SOURCES.txt
xhs_client.egg-info/dependency_links.txt
xhs_client.egg-info/not-zip-safe
xhs_client.egg-info/requires.txt
xhs_client.egg-info/top_level.txt