Metadata-Version: 2.1
Name: xhs-client
Version: 1.0.0
Summary: xiaohongshu crawl sdk.
Home-page: https://github.com:liusuxian/xhs
Author: liusuxian
Author-email: liusuxian89@gmail.com
License: MIT
Keywords: xhs crawl
Classifier: Development Status :: 3 - Alpha
Classifier: Intended Audience :: Developers
Classifier: License :: OSI Approved :: MIT License
Classifier: Programming Language :: Python
Classifier: Programming Language :: Python :: 3.8
Classifier: Programming Language :: Python :: 3.9
Classifier: Programming Language :: Python :: 3.10
Classifier: Programming Language :: Python :: 3.11
Classifier: Programming Language :: Python :: 3 :: Only
Classifier: Topic :: Software Development :: Libraries :: Python Modules
Requires-Python: >=3.7
License-File: LICENSE
